simple_rocket_chat_sender/__init__.py
simple_rocket_chat_sender/notification_service.py
simple_rocket_chat_sender-0.2.dist-info/LICENSE
simple_rocket_chat_sender-0.2.dist-info/METADATA
simple_rocket_chat_sender-0.2.dist-info/WHEEL
simple_rocket_chat_sender-0.2.dist-info/top_level.txt
simple_rocket_chat_sender-0.2.dist-info/RECORD
